Authors
ChangeLog
License
MANIFEST
setup.py
ez_setup/README.txt
ez_setup/__init__.py
iscpy/__init__.py
iscpy.egg-info/PKG-INFO
iscpy.egg-info/SOURCES.txt
iscpy.egg-info/dependency_links.txt
iscpy.egg-info/entry_points.txt
iscpy.egg-info/not-zip-safe
iscpy.egg-info/top_level.txt
iscpy/iscpy_core/__init__.py
iscpy/iscpy_core/core.py
iscpy/iscpy_dhcp/__init__.py
iscpy/iscpy_dns/__init__.py
iscpy/iscpy_dns/named_importer_lib.py
test/blank_named_regtest.py
test/named_importer_lib_regtest.py
test/test_data/named.example.conf