Metadata-Version: 1.0
Name: iscpy
Version: 1.05
Summary: Python library to parse ISC style config files.
Home-page: UNKNOWN
Author: Jacob C. Collins
Author-email: jc@purdue.edu
License: BSD
Keywords: isc config bind dhcp parser dns python
Platform: UNKNOWN
